{
  "antenna_id": "143224",
  "address": "ΝΟΤΙΟ ΤΜΗΜΑ ΣΗΡΑΓΓΑΣ ΚΛΟΚΟΒΑΣ,  Χ.Θ. 11+500 , ΙΟΝΙΑ ΟΔΟΣ",
  "position_code": 1237824,
  "municipality": "Ναυπακτίας",
  "code_name": "TUNNEL KLOKOVA  SOUTH INDOOR",
  "region": "Δυτικής Ελλάδας",
  "latitude": 38.354167,
  "company": "NOVA Μ.Α.Ε.",
  "longitude": 21.698333,
  "permit_status": "Από τα στοιχεία που τηρούνται στην Ενημερωτική Πύλη προκύπτει ότι, για τη θέση \"ΝΟΤΙΟ ΤΜΗΜΑ ΣΗΡΑΓΓΑΣ ΚΛΟΚΟΒΑΣ,  Χ.Θ. 11+500 , ΙΟΝΙΑ ΟΔΟΣ\" στον Δήμο Ναυπακτίας Περιφέρειας  Δυτικής Ελλάδας \n\t(κωδικός αριθμός θέσης 1237824, κωδική ονομασία \"TUNNEL KLOKOVA  SOUTH INDOOR\") έχει κατατεθεί από την εταιρία NOVA Μ.Α.Ε.\tδήλωση εγκατάστασης κατασκευής κεραίας (αριθ. πρωτ. \n\t33657/18-07-2019) που εμπίπτει στις διατάξεις της νομοθεσίας για Εγκαταστάσεις Κατασκευών Κεραιών Χαμηλής Ηλεκτρομαγνητικής Περιβαλλοντικής Όχλησης (ΕΚΚΧΟ).",
  "measurements_eaee": "-",
  "documents": [
    {
      "document_number": "371043/18-07-2019",
      "protocol_number": "ΣΚΑΡΙΦΗΜΑ ΚΕΡΑΙΩΝ ΕΚΚΧΟ/",
      "type": "Φωτογραφικό Υλικό - Σκαρίφημα",
      "file_url": "https://silia.eett.gr/silia/download/12c33d50-7f6e-45c5-825e-18d541ebcb9b"
    },
    {
      "document_number": "371055/18-07-2019",
      "protocol_number": "Αρχείο Αίτησης/",
      "type": "Δήλωση ΕΚΚΧΟ",
      "file_url": "https://silia.eett.gr/silia/download/94378587-4985-4373-b638-8f52348e27a7"
    }
  ]
}