{
  "antenna_id": "113370",
  "address": "Κανελλοπούλου 1,Ελευσίνα",
  "position_code": 1407299,
  "municipality": "Ελευσίνας",
  "code_name": "TITAN_ELEFS",
  "region": "Αττικής",
  "latitude": 38.04,
  "company": "OTE",
  "longitude": 23.533889,
  "permit_status": "Από τα στοιχεία που τηρούνται στην Ενημερωτική Πύλη προκύπτει ότι, για τη θέση \"Κανελλοπούλου 1,Ελευσίνα\" στον Δήμο Ελευσίνας Περιφέρειας  Αττικής \n\t(κωδικός αριθμός θέσης 1407299, κωδική ονομασία \"TITAN_ELEFS\") έχει κατατεθεί από την εταιρία OTE\tδήλωση εγκατάστασης κατασκευής κεραίας (αριθ. πρωτ. \n\t12378/28-08-2015) που εμπίπτει στις διατάξεις της νομοθεσίας για Εγκαταστάσεις Κατασκευών Κεραιών Χαμηλής Ηλεκτρομαγνητικής Περιβαλλοντικής Όχλησης (ΕΚΚΧΟ).",
  "measurements_eaee": "-",
  "documents": [
    {
      "document_number": "228543/28-08-2015",
      "protocol_number": "ΦΩΤΟΓΡΑΦΙΑ _ΕΚΚΧΟ/28-08-2015",
      "type": "Φωτογραφικό Υλικό - Σκαρίφημα",
      "file_url": "https://silia.eett.gr/silia/download/9c3a0455-5de4-4e70-9e52-ae0343986f01"
    },
    {
      "document_number": "228544/28-08-2015",
      "protocol_number": "Αρχείο Αίτησης/",
      "type": "Δήλωση ΕΚΚΧΟ",
      "file_url": "https://silia.eett.gr/silia/download/325b7be2-9d1f-4daa-880f-f7b14c850377"
    }
  ]
}