{
  "antenna_id": "125834",
  "address": "ΛΙΘΟΒΟΥΝΙ",
  "position_code": 20125,
  "municipality": "Αγρινίου",
  "code_name": "ΛΙΘΟΒΟΥΝΙ",
  "region": "Δυτικής Ελλάδας",
  "latitude": 38.504444,
  "company": "OTE",
  "longitude": 21.586944,
  "permit_status": "Από τα στοιχεία που τηρούνται στην Ενημερωτική Πύλη προκύπτει ότι, για τη θέση \"ΛΙΘΟΒΟΥΝΙ\" στον Δήμο Αγρινίου Περιφέρειας  Δυτικής Ελλάδας \n\t(κωδικός αριθμός θέσης 0020125, κωδική ονομασία \"ΛΙΘΟΒΟΥΝΙ\") έχει κατατεθεί από την εταιρία OTE\tδήλωση εγκατάστασης κατασκευής κεραίας (αριθ. πρωτ. \n\t21010/01-02-2017) που εμπίπτει στις διατάξεις της νομοθεσίας για Εγκαταστάσεις Κατασκευών Κεραιών Χαμηλής Ηλεκτρομαγνητικής Περιβαλλοντικής Όχλησης (ΕΚΚΧΟ).",
  "measurements_eaee": "-",
  "documents": [
    {
      "document_number": "285916/31-01-2017",
      "protocol_number": "ΜΕΣΩ ΣΗΛΥΑ/",
      "type": "Φωτογραφικό Υλικό - Σκαρίφημα",
      "file_url": "https://silia.eett.gr/silia/download/c9787889-6bf7-4e2e-a6f7-26c0b3cca61e"
    },
    {
      "document_number": "286034/01-02-2017",
      "protocol_number": "Αρχείο Αίτησης/",
      "type": "Δήλωση ΕΚΚΧΟ",
      "file_url": "https://silia.eett.gr/silia/download/e7f2b7ef-b9aa-4d7b-9509-d130f94fad3e"
    }
  ]
}