{
  "antenna_id": "81194",
  "address": "ΒΙΠΕ ΣΙΝΔΟΥ ΟΙΚ. ΤΕΤΡ. 22",
  "position_code": 1401499,
  "municipality": "Δέλτα",
  "code_name": "EGNATIWARE",
  "region": "Κεντρικής Μακεδονίας",
  "latitude": 40.692222,
  "company": "OTE",
  "longitude": 22.817778,
  "permit_status": "Από τα στοιχεία που τηρούνται στην Ενημερωτική Πύλη προκύπτει ότι, για τη θέση \"ΒΙΠΕ ΣΙΝΔΟΥ ΟΙΚ. ΤΕΤΡ. 22\" στον Δήμο Δέλτα Περιφέρειας  Κεντρικής Μακεδονίας \n\t(κωδικός αριθμός θέσης 1401499, κωδική ονομασία \"EGNATIWARE\") χορηγήθηκε, με την Απόφαση της ΕΕΤΤ \n15375/Φ610/05-03-2015, άδεια κατασκευής κεραίας στην εταιρία OTE. \nΑπό τo έγγραφο της άδειας μπορείτε να ενημερωθείτε για τις σχετικές εγκρίσεις των συναρμόδιων φορέων, καθώς και εάν πρόκειται για τροποποίηση παλαιότερης άδειας.\n\tΗ άδεια χορηγήθηκε κατόπιν της με Αριθ. Πρωτ. 42181/11-10-2010 αίτησης. \n\tΓια την έκδοση της άδειας εφαρμόστηκε το προγενέστερο του Ν.4053/2012 νομοθετικό πλαίσιο, καθώς κατά δήλωση της εταιρίας, η κατασκευή πληρούσε \nτις προϋποθέσεις του άρθρου 31 του Ν.4053/2012. \nΕπιπλέον, έχει υποβληθεί η με αριθ. πρωτ. ΣΗΛΥΑ 26261/14-02-2018 (Δήλωση παρ. 14 άρθρ. 60 ν. 4313/2014) δήλωση που αφορά σε τροποποίηση/επικαιροποίηση στοιχείων της κατασκευής κεραίας που αφορούν τον(ους) Τομέα(εις) Αδειοδότησης:Κεραιοσυστήματα, Περιβάλλον.\n\tΔιευκρινίζεται ότι υπό ορισμένες προϋποθέσεις για την τροποποίηση αδειοδοτημένης κατασκευής κεραίας ή/και την επικαιροποίηση στοιχείων της δεν απαιτείται η έκδοση νέας άδειας \n\tκατασκευής κεραίας ή η τροποποίηση της υφιστάμενης άδειας κατασκευής κεραίας, αλλά απαιτείται η υποβολή κατάλληλης δήλωσης από τον κάτοχο της κατασκευής κεραίας συνοδευόμενη \n\tαπό επικαιροποίηση επιμέρους εγκρίσεων. \n\t \tΣύμφωνα με τα στοιχεία που έχουν υποβληθεί στο ΣΗΛΥΑ για την κατασκευή κεραίας από τον κάτοχό της, έχει εκδοθεί έγκριση δομικών κατασκευών κεραίας",
  "measurements_eaee": "-",
  "documents": [
    {
      "document_number": "28101/16-11-2012",
      "protocol_number": "Μ.ι./411/3601/01-10-2010",
      "type": "Γνωμάτευση ΕΕΑΕ (νόμιμη λειτουργία)",
      "file_url": null
    },
    {
      "document_number": "33500/16-11-2012",
      "protocol_number": "12029/13-10-2010",
      "type": "Αίτηση / Μελέτη για Έγκριση Περιβαλλοντικών Επιπτώσεων",
      "file_url": null
    },
    {
      "document_number": "39140/16-11-2012",
      "protocol_number": "42181/11-10-2010",
      "type": "Αίτηση Άδειας Κατασκευής Κεραίας ΕΕΤΤ (νομίμως λειτουργούσα)",
      "file_url": "https://silia.eett.gr/silia/download/042ca3d9-8dbd-4bbb-8907-3c378aa9b222"
    },
    {
      "document_number": "60677/11-03-2013",
      "protocol_number": "Δ3/Δ/2264/16-03-2012",
      "type": "Γνωμάτευση ΥΠΑ",
      "file_url": "https://silia.eett.gr/silia/download/823240e1-b47e-4d4c-8c33-6b3f63a795a5"
    },
    {
      "document_number": "60678/11-03-2013",
      "protocol_number": "Δ3/Δ/8759/05-10-2010",
      "type": "Γνωμάτευση ΥΠΑ",
      "file_url": "https://silia.eett.gr/silia/download/78972392-627b-481f-815d-d50b3eedc2df"
    },
    {
      "document_number": "60679/11-03-2013",
      "protocol_number": "Δ3/Δ/25703/6964/27-07-2010",
      "type": "Γνωμάτευση ΥΠΑ",
      "file_url": "https://silia.eett.gr/silia/download/99d07495-341a-4568-8cd3-13c2def0900a"
    },
    {
      "document_number": "60680/11-03-2013",
      "protocol_number": "59/13-08-2010",
      "type": "Αποδεικτικό Καταβολής Τελών ΕΕΤΤ",
      "file_url": null
    },
    {
      "document_number": "60681/11-03-2013",
      "protocol_number": "215821/12180/25-10-2011",
      "type": "Έγκριση Περιβαλλοντικών Όρων",
      "file_url": "https://silia.eett.gr/silia/download/4bc2a3cf-241b-4cb9-89c1-e93688399f43"
    },
    {
      "document_number": "61401/15-03-2013",
      "protocol_number": "Αρχείο Αίτησης/",
      "type": "Αίτηση Άδειας Κατασκευής Κεραίας ΕΕΤΤ",
      "file_url": "https://silia.eett.gr/silia/download/d4af4dca-89a3-40a6-9c67-b4f7a924d0ce"
    },
    {
      "document_number": "85310/01-08-2013",
      "protocol_number": "12029/13.10.10/13-10-2010",
      "type": "Αίτηση / Μελέτη για Έγκριση Περιβαλλοντικών Επιπτώσεων (νόμιμη λειτουργία)",
      "file_url": null
    },
    {
      "document_number": "174158/20-05-2014",
      "protocol_number": "Μ.ι/411/3601/01-10-2010",
      "type": "Έγγραφο Αρμοδίου Φορέα",
      "file_url": "https://silia.eett.gr/silia/download/5b6f0a5e-8e94-424f-918e-708ad1035e01"
    },
    {
      "document_number": "199870/12-03-2015",
      "protocol_number": "15375/Φ610/05-03-2015",
      "type": "Άδεια Κατασκευής  Κεραίας",
      "file_url": "https://silia.eett.gr/silia/download/6b0369f4-fa2f-4931-ab90-3c452028ff38"
    },
    {
      "document_number": "333526/25-06-2018",
      "protocol_number": "28280/Φ610/08-06-2018",
      "type": "Διαπιστωτική Πράξη Υπαγωγής σε ΠΠΔ",
      "file_url": "https://silia.eett.gr/silia/download/3335d449-6534-4808-be85-3d93b95eea6b"
    },
    {
      "document_number": "496296/04-10-2023",
      "protocol_number": "14014990010060/26-08-2015",
      "type": "Έγκριση δομικών κατασκευών (έντυπη)",
      "file_url": "https://silia.eett.gr/silia/download/1c4e567d-9d95-48fe-a520-804653ae1849"
    },
    {
      "document_number": "320959/14-02-2018",
      "protocol_number": "ΜΕΣΩ ΣΗΛΥΑ/",
      "type": "Τοπογραφικό",
      "file_url": "https://silia.eett.gr/silia/download/2ac17114-8714-4a0d-8beb-08755a838fe0"
    },
    {
      "document_number": "320960/14-02-2018",
      "protocol_number": "ΜΕΣΩ ΣΗΛΥΑ/",
      "type": "Αρχιτεκτονικά Σχέδια",
      "file_url": "https://silia.eett.gr/silia/download/6369404e-5b43-47d1-85a4-cfd975022457"
    },
    {
      "document_number": "320961/14-02-2018",
      "protocol_number": "ΜΕΣΩ ΣΗΛΥΑ/14-12-2017",
      "type": "Αίτηση - Μελέτη Ραδιοεκπομπών ΕΕΑΕ",
      "file_url": "https://silia.eett.gr/silia/download/12348bf1-2ffc-43a2-9969-bcb5e308b9c8"
    },
    {
      "document_number": "320983/14-02-2018",
      "protocol_number": "Αρχείο Αίτησης/",
      "type": "Δήλωση Αναβάθμισης",
      "file_url": "https://silia.eett.gr/silia/download/10423919-7ab3-43da-97e6-7cac90d5df4a"
    },
    {
      "document_number": "328554/04-05-2018",
      "protocol_number": "Μ.ι./411/6007/2018/03-05-2018",
      "type": "Γνωμάτευση ΕΕΑΕ",
      "file_url": "https://silia.eett.gr/silia/download/a1c5dc62-57b6-4108-b431-75e28f7d9612"
    }
  ]
}