{
  "antenna_id": "113401",
  "address": "Σκάλα Ζαλόγγου, Βουνά Ζαλόγγου",
  "position_code": 9999999999,
  "municipality": "Πρέβεζας",
  "code_name": "ΖΑΛΟΓΓΟ",
  "region": "Ηπείρου",
  "latitude": 39.15,
  "company": "ΡΑΔΙΟ ΠΡΕΒΕΖΑ",
  "longitude": 20.695278,
  "permit_status": "Από τα στοιχεία που τηρούνται στην Ενημερωτική Πύλη προκύπτει ότι για τη  θέση \"Σκάλα Ζαλόγγου, Βουνά Ζαλόγγου\" στον Δήμο Πρέβεζας Περιφέρειας  Ηπείρου έχει κατατεθεί από τον ραδιοφωνικό σταθμό με την επωνυμία ΡΑΔΙΟ ΠΡΕΒΕΖΑ δήλωση κεραιοσυστημάτων ραδιοφωνικού σταθμού με αριθ. πρωτ. ΣΗΛΥΑ \n12400/01-09-2015.\n\nΗ δημοσιευμένη δηλωθείσα κατασκευή κεραίας νοείται ως νομίμως λειτουργούσα μόνο εφόσον πληρούνται σωρευτικά οι προϋποθέσεις της υπ’ αρ. 3 παραγράφου του άρθρου 61 του Ν. 4313/2014.",
  "measurements_eaee": "-",
  "documents": []
}