{
  "antenna_id": "109902",
  "address": "20ο χλμ ΑΘΗΝΩΝ - ΜΑΡΚΟΠΟΥΛΟΥ",
  "position_code": 1197307,
  "municipality": "Παιανίας",
  "code_name": "GRUNDFOS PAIANIA",
  "region": "Αττικής",
  "latitude": 37.937778,
  "company": "VODAFONE",
  "longitude": 23.8775,
  "permit_status": "Από τα στοιχεία που τηρούνται στην Ενημερωτική Πύλη προκύπτει ότι, για τη θέση \"20ο χλμ ΑΘΗΝΩΝ - ΜΑΡΚΟΠΟΥΛΟΥ\" στον Δήμο Παιανίας Περιφέρειας  Αττικής \n\t(κωδικός αριθμός θέσης 1197307, κωδική ονομασία \"GRUNDFOS PAIANIA\") έχει κατατεθεί από την εταιρία VODAFONE\tδήλωση εγκατάστασης κατασκευής κεραίας (αριθ. πρωτ. \n\t15935/15-05-2015) που εμπίπτει στις διατάξεις της νομοθεσίας για Εγκαταστάσεις Κατασκευών Κεραιών Χαμηλής Ηλεκτρομαγνητικής Περιβαλλοντικής Όχλησης (ΕΚΚΧΟ).",
  "measurements_eaee": "-",
  "documents": [
    {
      "document_number": "222428/23-07-2015",
      "protocol_number": "15935/15-05-2015",
      "type": "Δήλωση ΕΚΚΧΟ",
      "file_url": "https://silia.eett.gr/silia/download/b8429916-d482-4f44-b87f-0a8598a767ea"
    }
  ]
}