{
  "antenna_id": "133217",
  "address": "κορυφή Αέρας όρος Πάρνηθα",
  "position_code": 8000612,
  "municipality": "Αχαρνών",
  "code_name": "ΑΕΡΑΣ ΠΑΡΝΗΘΑΣ",
  "region": "Αττικής",
  "latitude": 38.144722,
  "company": "DIGITAL ICON",
  "longitude": 23.718333,
  "permit_status": "Από τα στοιχεία που τηρούνται στην Ενημερωτική Πύλη προκύπτει ότι, για τη θέση \"κορυφή Αέρας όρος Πάρνηθα\" στον Δήμο Αχαρνών Περιφέρειας  Αττικής \n\t(κωδικός αριθμός θέσης 8000612, κωδική ονομασία \"ΑΕΡΑΣ ΠΑΡΝΗΘΑΣ\") έχει κατατεθεί από την εταιρία DIGITAL ICON\tδήλωση εγκατάστασης κατασκευής κεραίας (αριθ. πρωτ. \n\t27717/30-05-2018) που εμπίπτει στις διατάξεις της νομοθεσίας για Εγκαταστάσεις Κατασκευών Κεραιών Χαμηλής Ηλεκτρομαγνητικής Περιβαλλοντικής Όχλησης (ΕΚΚΧΟ).",
  "measurements_eaee": "-",
  "documents": [
    {
      "document_number": "331065/30-05-2018",
      "protocol_number": "Σχέδιο όψης ΕΚΚΧΟ/30-05-2018",
      "type": "Φωτογραφικό Υλικό - Σκαρίφημα",
      "file_url": "https://silia.eett.gr/silia/download/7ff8edad-fdf2-4f28-aebc-771c46549698"
    },
    {
      "document_number": "331066/30-05-2018",
      "protocol_number": "Σχέδιο κάτοψης ΕΚΚΧΟ/30-05-2018",
      "type": "Φωτογραφικό Υλικό - Σκαρίφημα",
      "file_url": "https://silia.eett.gr/silia/download/c34b41de-2ac0-41f4-a54c-15fb7e4db6e7"
    },
    {
      "document_number": "331067/30-05-2018",
      "protocol_number": "Αρχείο Αίτησης/",
      "type": "Δήλωση ΕΚΚΧΟ",
      "file_url": "https://silia.eett.gr/silia/download/5de6cd38-e34b-44b9-a436-a383779eaf75"
    }
  ]
}